AUTHORS
LICENSE
MANIFEST.in
README.rst
setup.py
django_yandex_direct.egg-info/PKG-INFO
django_yandex_direct.egg-info/SOURCES.txt
django_yandex_direct.egg-info/dependency_links.txt
django_yandex_direct.egg-info/not-zip-safe
django_yandex_direct.egg-info/requires.txt
django_yandex_direct.egg-info/top_level.txt
yandex_direct/__init__.py
yandex_direct/defaults.py
yandex_direct/models.py