Metadata-Version: 1.1
Name: django-yandex-direct
Version: 1.0
Summary: Simple wrapper for the Yandex.Direct API
Home-page: https://github.com/LPgenerator/django-yandex-direct
Author: GoTLiuM InSPiRiT
Author-email: gotlium@gmail.com
License: UNKNOWN
Keywords: django yandex direct
Platform: UNKNOWN
Classifier: Development Status :: 5 - Production/Stable
Classifier: Environment :: Web Environment
Classifier: Framework :: Django
Classifier: Intended Audience :: Developers
Classifier: License :: OSI Approved :: GNU General Public License (GPL)
Classifier: Operating System :: OS Independent
Classifier: Programming Language :: Python
